{
  "summary": {
    "enKeys": 1968,
    "missingInFr": 105,
    "missingInEs": 242,
    "extraInFr": 83,
    "extraInEs": 76
  },
  "missingInFr": [
    "common.workflow.whyCompleteShort",
    "footer.links.downloadApp",
    "footer.links.privacyRadar",
    "footer.links.privacySettings",
    "footer.links.support",
    "homePage.hero.contextLine",
    "homePage.cta.analyzeYourFootprint",
    "homePage.cta.seeWhichServices",
    "homePage.alerts.intro",
    "homePage.alerts.addYourServices",
    "homePage.valueProposition.viewInCatalog",
    "homePage.valueProposition.viewAlerts",
    "howItWorks.startNoAccount",
    "howItWorks.cta.subtitleUpdated",
    "howItWorks.cta.titleCompleted",
    "howItWorks.cta.subtitleCompleted",
    "howItWorks.cta.startAssessment",
    "howItWorks.cta.viewDashboard",
    "howItWorks.cta.browseCatalog",
    "howItWorks.cta.downloadApp",
    "howItWorks.cta.selectServices",
    "howItWorks.cta.orTakeAssessment",
    "features.learnMore",
    "dashboard.pageTitle",
    "dashboard.whatYouCanDo",
    "dashboard.moreInApp",
    "dataBrokerRemoval.guideInfo.title",
    "dataBrokerRemoval.guideInfo.description",
    "serviceCatalog.outcomeLine",
    "serviceCatalog.seeFullCatalog",
    "serviceCatalog.riskMeanings.notAvailable",
    "serviceCatalog.notAvailable",
    "serviceCatalog.calculating",
    "serviceCatalog.ratedServicesDescription",
    "serviceCatalog.nonRatedServicesDescription",
    "serviceCatalog.notYetRated",
    "serviceCatalog.ratingComingSoon",
    "assessmentsPage.nextStepsTitle",
    "assessmentsPage.nextStepDashboard",
    "assessmentsPage.nextStepServices",
    "assessmentsPage.nextStepActionPlan",
    "assessmentsPage.whatYouGet",
    "privacySettingsPage.editPrivacyFocus",
    "account.subtitle",
    "account.name",
    "account.email",
    "account.profile",
    "account.dataPrivacy",
    "account.exportData",
    "account.subscription.title",
    "account.subscription.upgrade",
    "account.subscription.standard",
    "account.subscription.monthly",
    "account.subscription.renews",
    "account.subscription.provider",
    "account.subscription.manage",
    "account.subscription.cancel",
    "account.subscription.cancelStore",
    "account.subscription.cancelNote",
    "account.subscription.checking",
    "account.preferences.title",
    "account.preferences.notifications",
    "account.preferences.haptics",
    "account.privacyFirst.title",
    "account.privacyFirst.description",
    "account.clearData.title",
    "account.clearData.confirm",
    "account.resetSetup.title",
    "account.resetSetup.confirm",
    "account.help.feedback",
    "account.help.contact",
    "settings.theme.title",
    "settings.theme.light",
    "settings.theme.dark",
    "settings.language",
    "tutorials.viewAll",
    "tutorials.startTutorial",
    "tutorials.tutorials",
    "tutorials.availableTutorials",
    "tutorials.searchPlaceholder",
    "tutorials.noResults",
    "tutorials.noTutorials",
    "tutorials.tryDifferentSearch",
    "tutorials.noTutorialsAvailable",
    "support.subtitle",
    "support.resources.faq.title",
    "support.resources.faq.description",
    "support.resources.tutorial.title",
    "support.resources.tutorial.description",
    "support.resources.documentation.title",
    "support.resources.documentation.description",
    "support.resources.contact.title",
    "support.resources.contact.description",
    "support.quickHelp.title",
    "support.quickHelp.gettingStarted.title",
    "support.quickHelp.gettingStarted.item1",
    "support.quickHelp.gettingStarted.item2",
    "support.quickHelp.gettingStarted.item3",
    "support.quickHelp.commonQuestions.title",
    "support.quickHelp.commonQuestions.item1",
    "support.quickHelp.commonQuestions.item2",
    "support.quickHelp.commonQuestions.item3",
    "support.contact.title",
    "support.contact.description",
    "support.contact.button"
  ],
  "missingInEs": [
    "common.loading.text",
    "common.assessmentLimit.title",
    "common.assessmentLimit.description",
    "common.assessmentLimit.upgradeToPremium",
    "common.assessmentLimit.viewDashboard",
    "common.assessmentLimit.remainingWarning",
    "common.assessmentLimit.upgradeLink",
    "common.errorBoundary.title",
    "common.errorBoundary.description.production",
    "common.errorBoundary.description.development",
    "common.errorBoundary.errorId",
    "common.errorBoundary.feedbackLabel",
    "common.errorBoundary.feedbackPlaceholder",
    "common.errorBoundary.sendFeedback",
    "common.errorBoundary.feedbackThankYou",
    "common.errorBoundary.tryAgain",
    "common.errorBoundary.reload",
    "common.errorBoundary.home",
    "common.errorBoundary.needHelp",
    "common.errorBoundary.support",
    "common.errorBoundary.developerDetails",
    "common.errorBoundary.error",
    "common.errorBoundary.componentStack",
    "common.workflow.whyCompleteShort",
    "common.workflow.completionGuide.title",
    "common.workflow.completionGuide.progressLabel",
    "common.workflow.completionGuide.whyCompleteTitle",
    "common.workflow.completionGuide.whyCompleteDescription",
    "common.workflow.completionGuide.unlock1",
    "common.workflow.completionGuide.unlock2",
    "common.workflow.completionGuide.unlock3",
    "common.workflow.completionGuide.unlock4",
    "common.workflow.completionGuide.note",
    "common.workflow.completionGuide.noteText",
    "common.workflow.completionGuide.steps.browseServiceCatalog.title",
    "common.workflow.completionGuide.steps.browseServiceCatalog.description",
    "common.workflow.completionGuide.steps.setPrivacyConcerns.title",
    "common.workflow.completionGuide.steps.setPrivacyConcerns.description",
    "common.workflow.completionGuide.steps.completeAssessment.title",
    "common.workflow.completionGuide.steps.completeAssessment.description",
    "common.workflow.completionGuide.steps.accessDashboard.title",
    "common.workflow.completionGuide.steps.accessDashboard.description",
    "common.workflow.completionGuide.actions.view",
    "common.workflow.completionGuide.actions.start",
    "common.workflow.completionGuide.actions.locked",
    "footer.sections.help",
    "footer.links.downloadApp",
    "footer.links.privacyRadar",
    "footer.links.privacySettings",
    "footer.links.support",
    "footer.links.help",
    "homePage.hero.contextLine",
    "homePage.cta.analyzeYourFootprint",
    "homePage.cta.seeWhichServices",
    "homePage.alerts.intro",
    "homePage.alerts.addYourServices",
    "homePage.valueProposition.viewInCatalog",
    "homePage.valueProposition.viewAlerts",
    "howItWorks.startNoAccount",
    "howItWorks.cta.subtitleUpdated",
    "howItWorks.cta.titleCompleted",
    "howItWorks.cta.subtitleCompleted",
    "howItWorks.cta.startAssessment",
    "howItWorks.cta.viewDashboard",
    "howItWorks.cta.browseCatalog",
    "howItWorks.cta.downloadApp",
    "howItWorks.cta.selectServices",
    "howItWorks.cta.orTakeAssessment",
    "howItWorks.roadmap.title",
    "howItWorks.roadmap.description",
    "howItWorks.navigation.workflow",
    "howItWorks.navigation.assessments",
    "howItWorks.navigation.principles",
    "howItWorks.assessmentTypes.title",
    "howItWorks.assessmentTypes.subtitle",
    "howItWorks.assessmentTypes.digitalPrivacyRisk.title",
    "howItWorks.assessmentTypes.digitalPrivacyRisk.duration",
    "howItWorks.assessmentTypes.digitalPrivacyRisk.description",
    "howItWorks.assessmentTypes.digitalPrivacyRisk.features",
    "howItWorks.assessmentTypes.digitalPrivacyRisk.buttonText",
    "howItWorks.assessmentTypes.privacyRights.title",
    "howItWorks.assessmentTypes.privacyRights.duration",
    "howItWorks.assessmentTypes.privacyRights.description",
    "howItWorks.assessmentTypes.privacyRights.features",
    "howItWorks.assessmentTypes.privacyRights.buttonText",
    "howItWorks.assessmentTypes.securityAwareness.title",
    "howItWorks.assessmentTypes.securityAwareness.duration",
    "howItWorks.assessmentTypes.securityAwareness.description",
    "howItWorks.assessmentTypes.securityAwareness.features",
    "howItWorks.assessmentTypes.securityAwareness.buttonText",
    "features.learnMore",
    "dashboard.pageTitle",
    "dashboard.whatYouCanDo",
    "dashboard.moreInApp",
    "dataBrokerRemoval.guideInfo.title",
    "dataBrokerRemoval.guideInfo.description",
    "serviceCatalog.outcomeLine",
    "serviceCatalog.seeFullCatalog",
    "serviceCatalog.riskMeanings.notAvailable",
    "serviceCatalog.notAvailable",
    "serviceCatalog.calculating",
    "serviceCatalog.ratedServicesDescription",
    "serviceCatalog.nonRatedServicesDescription",
    "serviceCatalog.notYetRated",
    "serviceCatalog.ratingComingSoon",
    "toolkit.getPersonalizedRecommendations",
    "toolkit.browseExternalPrivacyTools",
    "toolkit.getServiceSpecificToolRecommendations",
    "toolkit.getServiceSpecificToolRecommendationsDesc",
    "toolkit.goToServicePrivacyCatalog",
    "toolkit.personalDataInventory",
    "toolkit.new",
    "toolkit.personalDataInventoryDesc",
    "toolkit.personalDataInventoryDescBold",
    "toolkit.openDataInventory",
    "toolkit.manageServices",
    "toolkit.personalDataInventoryTip",
    "toolkit.recommendedToolsForYourServices",
    "toolkit.recommendedToolsForYourServicesDesc",
    "toolkit.viewServicePrivacyCatalog",
    "contextualLinks.recommendedNextStep",
    "contextualLinks.suggestedNextSteps",
    "contextualLinks.priority",
    "contextualLinks.seeWhichServicesNeedTheseTools",
    "contextualLinks.learnMoreAboutTools",
    "assessmentsPage.headerTitle",
    "assessmentsPage.headerSubtitle",
    "assessmentsPage.yourProgress",
    "assessmentsPage.complete",
    "assessmentsPage.yourPrivacyJourney",
    "assessmentsPage.recommendedWorkflow",
    "assessmentsPage.recommendedWorkflowText",
    "assessmentsPage.serviceCatalog",
    "assessmentsPage.browseServiceCatalog",
    "assessmentsPage.browseServiceCatalogDesc",
    "assessmentsPage.browseServices",
    "assessmentsPage.selected",
    "assessmentsPage.takePrivacyAssessments",
    "assessmentsPage.viewYourDashboard",
    "assessmentsPage.viewYourDashboardDesc",
    "assessmentsPage.viewDashboard",
    "assessmentsPage.nextStepsTitle",
    "assessmentsPage.nextStepDashboard",
    "assessmentsPage.nextStepServices",
    "assessmentsPage.nextStepActionPlan",
    "assessmentsPage.whatYouGet",
    "assessmentsPage.whyTakeAssessments",
    "assessmentsPage.whyTakeAssessmentsText",
    "assessmentsPage.personaNote",
    "assessmentsPage.privacyRiskExposureAssessment.title",
    "assessmentsPage.privacyRiskExposureAssessment.subtitle",
    "assessmentsPage.privacyRiskExposureAssessment.completed",
    "assessmentsPage.privacyRiskExposureAssessment.duration",
    "assessmentsPage.privacyRiskExposureAssessment.description",
    "assessmentsPage.privacyRiskExposureAssessment.whatYoullLearn",
    "assessmentsPage.privacyRiskExposureAssessment.learn1",
    "assessmentsPage.privacyRiskExposureAssessment.learn2",
    "assessmentsPage.privacyRiskExposureAssessment.learn3",
    "assessmentsPage.privacyRiskExposureAssessment.retakeAssessment",
    "assessmentsPage.privacyRiskExposureAssessment.startAssessment",
    "assessmentsPage.privacyRightsKnowledgeCheckup.title",
    "assessmentsPage.privacyRightsKnowledgeCheckup.subtitle",
    "assessmentsPage.privacyRightsKnowledgeCheckup.completed",
    "assessmentsPage.privacyRightsKnowledgeCheckup.duration",
    "assessmentsPage.privacyRightsKnowledgeCheckup.description",
    "assessmentsPage.privacyRightsKnowledgeCheckup.whatYoullLearn",
    "assessmentsPage.privacyRightsKnowledgeCheckup.learn1",
    "assessmentsPage.privacyRightsKnowledgeCheckup.learn2",
    "assessmentsPage.privacyRightsKnowledgeCheckup.learn3",
    "assessmentsPage.privacyRightsKnowledgeCheckup.retakeCheckup",
    "assessmentsPage.privacyRightsKnowledgeCheckup.startCheckup",
    "assessmentsPage.yourPrivacyMatters.title",
    "assessmentsPage.yourPrivacyMatters.description",
    "privacySettingsPage.cookiePreferencesTitle",
    "privacySettingsPage.cookiePreferencesDesc",
    "privacySettingsPage.cookiePreferencesManage",
    "privacySettingsPage.cookieStatusAll",
    "privacySettingsPage.cookieStatusEssential",
    "privacySettingsPage.cookieStatusNotSet",
    "privacySettingsPage.editPrivacyFocus",
    "account.subtitle",
    "account.name",
    "account.email",
    "account.profile",
    "account.dataPrivacy",
    "account.exportData",
    "account.subscription.title",
    "account.subscription.upgrade",
    "account.subscription.standard",
    "account.subscription.monthly",
    "account.subscription.renews",
    "account.subscription.provider",
    "account.subscription.manage",
    "account.subscription.cancel",
    "account.subscription.cancelStore",
    "account.subscription.cancelNote",
    "account.subscription.checking",
    "account.preferences.title",
    "account.preferences.notifications",
    "account.preferences.haptics",
    "account.privacyFirst.title",
    "account.privacyFirst.description",
    "account.clearData.title",
    "account.clearData.confirm",
    "account.resetSetup.title",
    "account.resetSetup.confirm",
    "account.help.feedback",
    "account.help.contact",
    "settings.theme.title",
    "settings.theme.light",
    "settings.theme.dark",
    "settings.language",
    "tutorials.viewAll",
    "tutorials.startTutorial",
    "tutorials.tutorials",
    "tutorials.availableTutorials",
    "tutorials.searchPlaceholder",
    "tutorials.noResults",
    "tutorials.noTutorials",
    "tutorials.tryDifferentSearch",
    "tutorials.noTutorialsAvailable",
    "support.subtitle",
    "support.resources.faq.title",
    "support.resources.faq.description",
    "support.resources.tutorial.title",
    "support.resources.tutorial.description",
    "support.resources.documentation.title",
    "support.resources.documentation.description",
    "support.resources.contact.title",
    "support.resources.contact.description",
    "support.quickHelp.title",
    "support.quickHelp.gettingStarted.title",
    "support.quickHelp.gettingStarted.item1",
    "support.quickHelp.gettingStarted.item2",
    "support.quickHelp.gettingStarted.item3",
    "support.quickHelp.commonQuestions.title",
    "support.quickHelp.commonQuestions.item1",
    "support.quickHelp.commonQuestions.item2",
    "support.quickHelp.commonQuestions.item3",
    "support.contact.title",
    "support.contact.description",
    "support.contact.button"
  ],
  "extraInFr": [
    "common.navigation.persona",
    "common.workflow.findPersona",
    "common.workflow.findPersonaDesc",
    "common.workflow.completionGuide.personaSubtitle",
    "common.workflow.completionGuide.steps.selectPersona.title",
    "common.workflow.completionGuide.steps.selectPersona.description",
    "header.ariaLabels.persona",
    "header.ariaLabels.selectPersona",
    "footer.links.choosePersona",
    "homePage.hero.selectPersona",
    "homePage.hero.selectPersonaShort",
    "homePage.personas.title",
    "homePage.personas.subtitle",
    "homePage.personas.currentPersona",
    "homePage.personas.howPersonasWork",
    "homePage.personas.selectYourPersona",
    "homePage.personas.selectYourPersonaDesc",
    "homePage.personas.customizeYourFocus",
    "homePage.personas.customizeYourFocusDesc",
    "homePage.personas.personalizedExperience",
    "homePage.personas.personalizedExperienceDesc",
    "homePage.personas.exploreAllPersonas",
    "homePage.personas.discoverYourPersona",
    "homePage.personas.personaOptional",
    "homePage.journey.selectPersona",
    "homePage.journey.selectPersonaDesc",
    "homePage.featuresSection.personaBased.title",
    "homePage.featuresSection.personaBased.subtitle",
    "homePage.featuresSection.personaBased.description",
    "homePage.featuresSection.personaBased.benefit1",
    "homePage.featuresSection.personaBased.benefit2",
    "homePage.featuresSection.personaBased.benefit3",
    "homePage.featuresSection.personaBased.benefit4",
    "homePage.featuresSection.personaBased.detailedDescription",
    "homePage.featuresSection.personaBased.howToAccess",
    "homePage.featuresSection.personaBased.actionLabel",
    "homePage.trustIndicators.privacyPersonas",
    "homePage.trustIndicators.privacyPersonasSubLabel",
    "features.aiPersona.title",
    "features.aiPersona.subtitle",
    "features.aiPersona.description",
    "features.aiPersona.benefits",
    "features.aiPersona.learnMore",
    "features.sevenPersonas.title",
    "features.sevenPersonas.subtitle",
    "features.sevenPersonas.description",
    "features.sevenPersonas.benefits",
    "personaSelection.title",
    "personaSelection.subtitle",
    "personaSelection.current",
    "personaSelection.whyMatters.title",
    "personaSelection.whyMatters.personalized.title",
    "personaSelection.whyMatters.personalized.description",
    "personaSelection.whyMatters.saveTime.title",
    "personaSelection.whyMatters.saveTime.description",
    "personaSelection.whyMatters.relevantLearning.title",
    "personaSelection.whyMatters.relevantLearning.description",
    "personaSelection.preview.title",
    "personaSelection.preview.primaryConcerns",
    "personaSelection.preview.whatYoullGet",
    "personaSelection.preview.personalizedDashboard",
    "personaSelection.preview.relevantResources",
    "personaSelection.preview.targetedTools",
    "personaSelection.preview.customizedPlans",
    "personaSelection.actions.continue",
    "personaSelection.actions.update",
    "personaSelection.actions.settingUp",
    "personaSelection.actions.skip",
    "personaSelection.helpText",
    "dataBrokerRemoval.realTool.title",
    "dataBrokerRemoval.realTool.description",
    "serviceCatalog.selectPersona",
    "serviceCatalog.selectPersonaButton",
    "serviceCatalog.personalizationPrompt.selectPersona",
    "assessmentsPage.selectYourPersona",
    "assessmentsPage.selectYourPersonaDesc",
    "assessmentsPage.selectPersona",
    "assessmentsPage.viewAllPersonas",
    "privacySettingsPage.yourPrivacyPersona",
    "privacySettingsPage.selectYourPersona",
    "faq.howItWorks.personaAccuracyAnswer",
    "faq.howItWorks.changePersonaQuestion",
    "faq.howItWorks.changePersonaAnswer"
  ],
  "extraInEs": [
    "common.navigation.persona",
    "common.workflow.findPersona",
    "common.workflow.findPersonaDesc",
    "header.ariaLabels.persona",
    "header.ariaLabels.selectPersona",
    "footer.links.choosePersona",
    "homePage.hero.selectPersona",
    "homePage.hero.selectPersonaShort",
    "homePage.personas.title",
    "homePage.personas.subtitle",
    "homePage.personas.currentPersona",
    "homePage.personas.howPersonasWork",
    "homePage.personas.selectYourPersona",
    "homePage.personas.selectYourPersonaDesc",
    "homePage.personas.customizeYourFocus",
    "homePage.personas.customizeYourFocusDesc",
    "homePage.personas.personalizedExperience",
    "homePage.personas.personalizedExperienceDesc",
    "homePage.personas.exploreAllPersonas",
    "homePage.personas.discoverYourPersona",
    "homePage.personas.personaOptional",
    "homePage.journey.selectPersona",
    "homePage.journey.selectPersonaDesc",
    "homePage.featuresSection.personaBased.title",
    "homePage.featuresSection.personaBased.subtitle",
    "homePage.featuresSection.personaBased.description",
    "homePage.featuresSection.personaBased.benefit1",
    "homePage.featuresSection.personaBased.benefit2",
    "homePage.featuresSection.personaBased.benefit3",
    "homePage.featuresSection.personaBased.benefit4",
    "homePage.featuresSection.personaBased.detailedDescription",
    "homePage.featuresSection.personaBased.howToAccess",
    "homePage.featuresSection.personaBased.actionLabel",
    "homePage.trustIndicators.privacyPersonas",
    "homePage.trustIndicators.privacyPersonasSubLabel",
    "features.aiPersona.title",
    "features.aiPersona.subtitle",
    "features.aiPersona.description",
    "features.aiPersona.benefits",
    "features.aiPersona.learnMore",
    "features.sevenPersonas.title",
    "features.sevenPersonas.subtitle",
    "features.sevenPersonas.description",
    "features.sevenPersonas.benefits",
    "personaSelection.title",
    "personaSelection.subtitle",
    "personaSelection.current",
    "personaSelection.whyMatters.title",
    "personaSelection.whyMatters.personalized.title",
    "personaSelection.whyMatters.personalized.description",
    "personaSelection.whyMatters.saveTime.title",
    "personaSelection.whyMatters.saveTime.description",
    "personaSelection.whyMatters.relevantLearning.title",
    "personaSelection.whyMatters.relevantLearning.description",
    "personaSelection.preview.title",
    "personaSelection.preview.primaryConcerns",
    "personaSelection.preview.whatYoullGet",
    "personaSelection.preview.personalizedDashboard",
    "personaSelection.preview.relevantResources",
    "personaSelection.preview.targetedTools",
    "personaSelection.preview.customizedPlans",
    "personaSelection.actions.continue",
    "personaSelection.actions.update",
    "personaSelection.actions.settingUp",
    "personaSelection.actions.skip",
    "personaSelection.helpText",
    "dataBrokerRemoval.realTool.title",
    "dataBrokerRemoval.realTool.description",
    "serviceCatalog.selectPersona",
    "serviceCatalog.selectPersonaButton",
    "serviceCatalog.personalizationPrompt.selectPersona",
    "privacySettingsPage.yourPrivacyPersona",
    "privacySettingsPage.selectYourPersona",
    "faq.howItWorks.personaAccuracyAnswer",
    "faq.howItWorks.changePersonaQuestion",
    "faq.howItWorks.changePersonaAnswer"
  ]
}